README.rst
setup.py
./zca_snippets/__init__.py
./zca_snippets/detector.py
./zca_snippets/list.py
./zca_snippets/snippets.py
zca_snippets.egg-info/PKG-INFO
zca_snippets.egg-info/SOURCES.txt
zca_snippets.egg-info/dependency_links.txt
zca_snippets.egg-info/entry_points.txt
zca_snippets.egg-info/requires.txt
zca_snippets.egg-info/top_level.txt