Metadata-Version: 1.1
Name: zca-snippets
Version: 0.0.2
Summary: snippets for zope.interface
Home-page: UNKNOWN
Author: podhmo
Author-email: UNKNOWN
License: UNKNOWN
Platform: UNKNOWN
Classifier: Programming Language :: Python
Classifier: Programming Language :: Python :: 3
